pynuget/__init__.py
pynuget/__main__.py
pynuget/_logging.py
pynuget/app_factory.py
pynuget/cli.py
pynuget/commands.py
pynuget/core.py
pynuget/db.py
pynuget/default_config.py
pynuget/feedwriter.py
pynuget/routes.py
pynuget/templates/web/_layout.html
pynuget/templates/web/index.html
pynuget-0.2.5.data/data/data/apache-example.conf
pynuget-0.2.5.data/data/data/wsgi.py
pynuget-0.2.5.dist-info/LICENSE.txt
pynuget-0.2.5.dist-info/METADATA
pynuget-0.2.5.dist-info/RECORD
pynuget-0.2.5.dist-info/WHEEL
pynuget-0.2.5.dist-info/entry_points.txt
pynuget-0.2.5.dist-info/top_level.txt
