Metadata-Version: 2.1
Name: pynuget
Version: 0.2.5
Summary: A Python-based NuGet Server
Home-page: https://github.com/dougthor42/pynuget/
Author: Douglas Thor
Author-email: doug.thor@gmail.com
License: UNKNOWN
Keywords: nuget packaging c# csharp
Platform: UNKNOWN
Classifier: Development Status :: 4 - Beta
Classifier: Intended Audience :: Developers
Classifier: Intended Audience :: Information Technology
Classifier: Intended Audience :: System Administrators
Classifier: License :: OSI Approved :: MIT License
Classifier: Operating System :: POSIX :: Linux
Classifier: Programming Language :: Python :: 3.5
Classifier: Programming Language :: Python :: 3.6
Classifier: Programming Language :: Python :: 3.7
Classifier: Programming Language :: Python :: 3 :: Only
Classifier: Programming Language :: Python :: Implementation :: CPython
Classifier: Topic :: Internet :: WWW/HTTP :: WSGI :: Application
Classifier: Topic :: Software Development :: Build Tools
Requires-Python: >=3.5
Requires-Dist: sqlalchemy (>=1.2.7)
Requires-Dist: flask (>=0.12.2)
Requires-Dist: lxml (>=4.2.1)
Requires-Dist: requests (>=2.19.1)
